src/mario_exercises/traffic_light.v
// Mercedes. Leonel.

module traffic_light(
    input clk,
    input avl,
    output reg red,
    output reg green,
    output reg blue
    );
    reg[5:0] counter = 5'd0;
    
    // If the clock is high 
    always@(posedge clk) begin
        
        // The switch is available
        if(avl == 1) begin
            // Red light should last 10 clock cycles, followed by yellow of 2 cycles, 
            // followed by green of 8 cycles, followed by yellow of 5 cycles
            
            if( counter == 0) begin        // red
                red = 1;
            end
            
            if( counter == 10) begin       // yellow
                // red + green = yellow LED
                green = 1;
            end
                
            if(counter == 12) begin        // green
                red = 0;
                green = 1;
            end
            
            if(counter == 20) begin        // yellow
                red = 1;
            end
                 
            // Increment the counter
            counter <= counter + 5'd1;
            
            // Reset the counter when it completes all the instructions
            if(counter == 25) begin
                counter <= 5'd0;    
            end      
        end
        else begin
            counter <= 5'd0;
        end
    end

endmodule

src/mario_exercises/traffic_light_tb.v
// Mercedes. Leonel.

`timescale 1ns / 1ps

module testbench;
 // Inputs
 reg clk;
 reg avl = 1;
    
 // Outputs
 wire red;
 wire green;
 wire blue;
 
 integer k = 0;
    
 initial begin

    // $dumpfile("traffic_light_tb.vcd");
    // $dumpvars(0, testbench);

    clk = 0;
    forever #5 clk = ~clk;
    
    //for (k=0; k < 50; k = k+1)
    //#10
 end
 
always @(posedge clk) begin
    k = k + 1;
    if (k == 50) begin
        $finish;
     end 
end

//initial begin
//    k = 0;
//end
 
 traffic_light uut (clk, avl, red, green, blue);

endmodule

src/mario_exercises/traffic_light_tb.vcd
$date
	Tue Jun  3 02:23:12 2025
$end
$version
	Icarus Verilog
$end
$timescale
	1ps
$end
$scope module testbench $end
$var wire 1 ! red $end
$var wire 1 " green $end
$var wire 1 # blue $end
$var reg 1 $ avl $end
$var reg 1 % clk $end
$var integer 32 & k [31:0] $end
$scope module uut $end
$var wire 1 $ avl $end
$var wire 1 % clk $end
$var reg 1 # blue $end
$var reg 6 ' counter [5:0] $end
$var reg 1 " green $end
$var reg 1 ! red $end
$upscope $end
$upscope $end
$enddefinitions $end
#0
$dumpvars
b0 '
b0 &
0%
1$
x#
x"
x!
$end
#5000
b1 '
1!
b1 &
1%
#10000
0%
#15000
b10 '
b10 &
1%
#20000
0%
#25000
b11 '
b11 &
1%
#30000
0%
#35000
b100 '
b100 &
1%
#40000
0%
#45000
b101 '
b101 &
1%
#50000
0%
#55000
b110 '
b110 &
1%
#60000
0%
#65000
b111 '
b111 &
1%
#70000
0%
#75000
b1000 '
b1000 &
1%
#80000
0%
#85000
b1001 '
b1001 &
1%
#90000
0%
#95000
b1010 '
b1010 &
1%
#100000
0%
#105000
b1011 '
1"
b1011 &
1%
#110000
0%
#115000
b1100 '
b1100 &
1%
#120000
0%
#125000
b1101 '
0!
b1101 &
1%
#130000
0%
#135000
b1110 '
b1110 &
1%
#140000
0%
#145000
b1111 '
b1111 &
1%
#150000
0%
#155000
b10000 '
b10000 &
1%
#160000
0%
#165000
b10001 '
b10001 &
1%
#170000
0%
#175000
b10010 '
b10010 &
1%
#180000
0%
#185000
b10011 '
b10011 &
1%
#190000
0%
#195000
b10100 '
b10100 &
1%
#200000
0%
#205000
b10101 '
1!
b10101 &
1%
#210000
0%
#215000
b10110 '
b10110 &
1%
#220000
0%
#225000
b10111 '
b10111 &
1%
#230000
0%
#235000
b11000 '
b11000 &
1%
#240000
0%
#245000
b11001 '
b11001 &
1%
#250000
0%
#255000
b0 '
b11010 &
1%
#260000
0%
#265000
b1 '
b11011 &
1%
#270000
0%
#275000
b10 '
b11100 &
1%
#280000
0%
#285000
b11 '
b11101 &
1%
#290000
0%
#295000
b100 '
b11110 &
1%
#300000
0%
#305000
b101 '
b11111 &
1%
#310000
0%
#315000
b110 '
b100000 &
1%
#320000
0%
#325000
b111 '
b100001 &
1%
#330000
0%
#335000
b1000 '
b100010 &
1%
#340000
0%
#345000
b1001 '
b100011 &
1%
#350000
0%
#355000
b1010 '
b100100 &
1%
#360000
0%
#365000
b1011 '
b100101 &
1%
#370000
0%
#375000
b1100 '
b100110 &
1%
#380000
0%
#385000
b1101 '
0!
b100111 &
1%
#390000
0%
#395000
b1110 '
b101000 &
1%
#400000
0%
#405000
b1111 '
b101001 &
1%
#410000
0%
#415000
b10000 '
b101010 &
1%
#420000
0%
#425000
b10001 '
b101011 &
1%
#430000
0%
#435000
b10010 '
b101100 &
1%
#440000
0%
#445000
b10011 '
b101101 &
1%
#450000
0%
#455000
b10100 '
b101110 &
1%
#460000
0%
#465000
b10101 '
1!
b101111 &
1%
#470000
0%
#475000
b10110 '
b110000 &
1%
#480000
0%
#485000
b10111 '
b110001 &
1%
#490000
0%
#495000
b11000 '
b110010 &
1%
